kefrey
