Metadata-Version: 1.1
Name: kefrey
Version: 0.1.1
Summary: A tool to track system-wide keypress frequencies
Home-page: https://github.com/matthewscholefield/kefrey
Author: Matthew D. Scholefield
Author-email: matthew331199@gmail.com
License: UNKNOWN
Keywords: kefrey
Platform: UNKNOWN
Classifier: Development Status :: 3 - Alpha
Classifier: Intended Audience :: Developers
Classifier: Programming Language :: Python :: 3
Classifier: Programming Language :: Python :: 3.4
Classifier: Programming Language :: Python :: 3.5
Classifier: Programming Language :: Python :: 3.6
